{"index": ["Abreu e Lima", "Afogados da Ingazeira", "Afrânio", "Agrestina", "Água Preta", "Águas Belas", "Alagoinha", "Aliança", "Altinho", "Amaraji", "Angelim", "Araçoiaba", "Araripina", "Arcoverde", "Barra de Guabiraba", "Barreiros", "Belém de Maria", "Belém do São Francisco", "Belo Jardim", "Betânia", "Bezerros", "Bodocó", "Bom Conselho", "Bom Jardim", "Bonito", "Brejão", "Brejinho", "Brejo da Madre de Deus", "Buenos Aires", "Buíque", "Cabo de Santo Agostinho", "Cabrobó", "Cachoeirinha", "Caetés", "Calçado", "Calumbi", "Camaragibe", "Camocim de São Félix", "Camutanga", "Canhotinho", "Capoeiras", "Carnaíba", "Carnaubeira da Penha", "Carpina", "Caruaru", "Casinhas", "Catende", "Cedro", "Chã de Alegria", "Chã Grande", "Condado", "Correntes", "Cortês", "Cumaru", "Cupira", "Custódia", "Dormentes", "Escada", "Exu", "Feira Nova", "Fernando de Noronha", "Ferreiros", "Flores", "Floresta", "Frei Miguelinho", "Gameleira", "Garanhuns", "Glória do Goitá", "Goiana", "Granito", "Gravatá", "Iati", "Ibimirim", "Ibirajuba", "Igarassu", "Iguaracy", "Inajá", "Ingazeira", "Ipojuca", "Ipubi", "Itacuruba", "Itaíba", "Ilha de Itamaracá", "Itambé", "Itapetim", "Itapissuma", "Itaquitinga", "Jaboatão dos Guararapes", "Jaqueira", "Jataúba", "Jatobá", "João Alfredo", "Joaquim Nabuco", "Jucati", "Jupi", "Jurema", "Lagoa do Carro", "Lagoa de Itaenga", "Lagoa do Ouro", "Lagoa dos Gatos", "Lagoa Grande", "Lajedo", "Limoeiro", "Macaparana", "Machados", "Manari", "Maraial", "Mirandiba", "Moreno", "Nazaré da Mata", "Olinda", "Orobó", "Orocó", "Ouricuri", "Palmares", "Palmeirina", "Panelas", "Paranatama", "Parnamirim", "Passira", "Paudalho", "Paulista", "Pedra", "Pesqueira", "Petrolândia", "Petrolina", "Poção", "Pombos", "Primavera", "Quipapá", "Quixaba", "Recife", "Riacho das Almas", "Ribeirão", "Rio Formoso", "Sairé", "Salgadinho", "Salgueiro", "Saloá", "Sanharó", "Santa Cruz", "Santa Cruz da Baixa Verde", "Santa Cruz do Capibaribe", "Santa Filomena", "Santa Maria da Boa Vista", "Santa Maria do Cambucá", "Santa Terezinha", "São Benedito do Sul", "São Bento do Una", "São Caitano", "São João", "São Joaquim do Monte", "São José da Coroa Grande", "São José do Belmonte", "São José do Egito", "São Lourenço da Mata", "São Vicente Férrer", "Serra Talhada", "Serrita", "Sertânia", "Sirinhaém", "Moreilândia", "Solidão", "Surubim", "Tabira", "Tacaimbó", "Tacaratu", "Tamandaré", "Taquaritinga do Norte", "Terezinha", "Terra Nova", "Timbaúba", "Toritama", "Tracunhaém", "Trindade", "Triunfo", "Tupanatinga", "Tuparetama", "Venturosa", "Verdejante", "Vertente do Lério", "Vertentes", "Vicência", "Vitória de Santo Antão", "Xexéu"], "dataset": [{"Densidade_demográfica": 748.29, "Salário_médio_mensal_dos_trabalhadores_formais": 2.0, "População_ocupada": 12.8, "Taxa_de_escolarização_de_6_a_14_anos_de_idade": 97.2, "Mortalidade_Infantil": 7.24, "Esgotamento_sanitário_adequado": 44.8}, {"Densidade_demográfica": 92.9, "Salário_médio_mensal_dos_trabalhadores_formais": 1.8, "População_ocupada": 10.3, "Taxa_de_escolarização_de_6_a_14_anos_de_idade": 97.3, "Mortalidade_Infantil": 13.41, "Esgotamento_sanitário_adequado": 71.0}, {"Densidade_demográfica": 11.8, "Salário_médio_mensal_dos_trabalhadores_formais": 1.5, "População_ocupada": 7.9, "Taxa_de_escolarização_de_6_a_14_anos_de_idade": 98.7, "Mortalidade_Infantil": 23.08, "Esgotamento_sanitário_adequado": 24.2}, {"Densidade_demográfica": 112.58, "Salário_médio_mensal_dos_trabalhadores_formais": 1.5, "População_ocupada": 7.2, "Taxa_de_escolarização_de_6_a_14_anos_de_idade": 96.4, "Mortalidade_Infantil": 5.92, "Esgotamento_sanitário_adequado": 67.8}, {"Densidade_demográfica": 62.05, "Salário_médio_mensal_dos_trabalhadores_formais": 1.6, "População_ocupada": 5.3, "Taxa_de_escolarização_de_6_a_14_anos_de_idade": 94.0, "Mortalidade_Infantil": 6.17, "Esgotamento_sanitário_adequado": 40.6}, {"Densidade_demográfica": 45.41, "Salário_médio_mensal_dos_trabalhadores_formais": 1.8, "População_ocupada": 4.6, "Taxa_de_escolarização_de_6_a_14_anos_de_idade": 96.1, "Mortalidade_Infantil": 20.86, "Esgotamento_sanitário_adequado": 29.1}, {"Densidade_demográfica": 63.16, "Salário_médio_mensal_dos_trabalhadores_formais": 1.5, "População_ocupada": 6.1, "Taxa_de_escolarização_de_6_a_14_anos_de_idade": 96.3, "Mortalidade_Infantil": 10.81, "Esgotamento_sanitário_adequado": 47.9}, {"Densidade_demográfica": 137.16, "Salário_médio_mensal_dos_trabalhadores_formais": 1.4, "População_ocupada": 9.2, "Taxa_de_escolarização_de_6_a_14_anos_de_idade": 97.0, "Mortalidade_Infantil": 13.33, "Esgotamento_sanitário_adequado": 55.8}, {"Densidade_demográfica": 49.18, "Salário_médio_mensal_dos_trabalhadores_formais": 1.7, "População_ocupada": 5.6, "Taxa_de_escolarização_de_6_a_14_anos_de_idade": 96.9, "Mortalidade_Infantil": 21.58, "Esgotamento_sanitário_adequado": 52.4}, {"Densidade_demográfica": 93.37, "Salário_médio_mensal_dos_trabalhadores_formais": 1.6, "População_ocupada": 8.1, "Taxa_de_escolarização_de_6_a_14_anos_de_idade": 96.6, "Mortalidade_Infantil": 19.74, "Esgotamento_sanitário_adequado": 50.8}, {"Densidade_demográfica": 86.43, "Salário_médio_mensal_dos_trabalhadores_formais": 2.1, "População_ocupada": 7.3, "Taxa_de_escolarização_de_6_a_14_anos_de_idade": 96.4, "Mortalidade_Infantil": 23.26, "Esgotamento_sanitário_adequado": 54.7}, {"Densidade_demográfica": 188.38, "Salário_médio_mensal_dos_trabalhadores_formais": 1.6, "População_ocupada": 6.9, "Taxa_de_escolarização_de_6_a_14_anos_de_idade": 97.0, "Mortalidade_Infantil": 13.2, "Esgotamento_sanitário_adequado": 9.3}, {"Densidade_demográfica": 40.84, "Salário_médio_mensal_dos_trabalhadores_formais": 1.8, "População_ocupada": 9.7, "Taxa_de_escolarização_de_6_a_14_anos_de_idade": 95.2, "Mortalidade_Infantil": 12.66, "Esgotamento_sanitário_adequado": 45.6}, {"Densidade_demográfica": 196.05, "Salário_médio_mensal_dos_trabalhadores_formais": 1.9, "População_ocupada": 12.7, "Taxa_de_escolarização_de_6_a_14_anos_de_idade": 97.3, "Mortalidade_Infantil": 27.63, "Esgotamento_sanitário_adequado": 86.4}, {"Densidade_demográfica": 111.43, "Salário_médio_mensal_dos_trabalhadores_formais": 1.4, "População_ocupada": 36.1, "Taxa_de_escolarização_de_6_a_14_anos_de_idade": 93.7, "Mortalidade_Infantil": 5.75, "Esgotamento_sanitário_adequado": 74.5}, {"Densidade_demográfica": 174.54, "Salário_médio_mensal_dos_trabalhadores_formais": 1.7, "População_ocupada": 10.5, "Taxa_de_escolarização_de_6_a_14_anos_de_idade": 94.6, "Mortalidade_Infantil": 15.67, "Esgotamento_sanitário_adequado": 44.2}, {"Densidade_demográfica": 153.96, "Salário_médio_mensal_dos_trabalhadores_formais": 1.7, "População_ocupada": 3.5, "Taxa_de_escolarização_de_6_a_14_anos_de_idade": 98.5, "Mortalidade_Infantil": 8.06, "Esgotamento_sanitário_adequado": 43.7}, {"Densidade_demográfica": 11.06, "Salário_médio_mensal_dos_trabalhadores_formais": 1.7, "População_ocupada": 13.5, "Taxa_de_escolarização_de_6_a_14_anos_de_idade": 97.3, "Mortalidade_Infantil": 16.13, "Esgotamento_sanitário_adequado": 42.6}, {"Densidade_demográfica": 111.83, "Salário_médio_mensal_dos_trabalhadores_formais": 2.0, "População_ocupada": 17.7, "Taxa_de_escolarização_de_6_a_14_anos_de_idade": 97.1, "Mortalidade_Infantil": 10.36, "Esgotamento_sanitário_adequado": 70.8}, {"Densidade_demográfica": 9.65, "Salário_médio_mensal_dos_trabalhadores_formais": 1.8, "População_ocupada": 5.3, "Taxa_de_escolarização_de_6_a_14_anos_de_idade": 93.8, "Mortalidade_Infantil": 21.62, "Esgotamento_sanitário_adequado": 32.8}, {"Densidade_demográfica": 119.53, "Salário_médio_mensal_dos_trabalhadores_formais": 1.5, "População_ocupada": 23.3, "Taxa_de_escolarização_de_6_a_14_anos_de_idade": 95.9, "Mortalidade_Infantil": 7.84, "Esgotamento_sanitário_adequado": 73.0}, {"Densidade_demográfica": 21.75, "Salário_médio_mensal_dos_trabalhadores_formais": 1.8, "População_ocupada": 4.9, "Taxa_de_escolarização_de_6_a_14_anos_de_idade": 95.7, "Mortalidade_Infantil": 18.52, "Esgotamento_sanitário_adequado": 24.5}, {"Densidade_demográfica": 57.44, "Salário_médio_mensal_dos_trabalhadores_formais": 1.9, "População_ocupada": 6.1, "Taxa_de_escolarização_de_6_a_14_anos_de_idade": 96.2, "Mortalidade_Infantil": 21.31, "Esgotamento_sanitário_adequado": 54.4}, {"Densidade_demográfica": 169.49, "Salário_médio_mensal_dos_trabalhadores_formais": 1.4, "População_ocupada": 5.6, "Taxa_de_escolarização_de_6_a_14_anos_de_idade": 97.0, "Mortalidade_Infantil": 2.07, "Esgotamento_sanitário_adequado": 22.1}, {"Densidade_demográfica": 94.96, "Salário_médio_mensal_dos_trabalhadores_formais": 1.8, "População_ocupada": 6.4, "Taxa_de_escolarização_de_6_a_14_anos_de_idade": 96.7, "Mortalidade_Infantil": 6.38, "Esgotamento_sanitário_adequado": 65.4}, {"Densidade_demográfica": 55.35, "Salário_médio_mensal_dos_trabalhadores_formais": 1.7, "População_ocupada": 7.3, "Taxa_de_escolarização_de_6_a_14_anos_de_idade": 96.3, "Mortalidade_Infantil": 18.63, "Esgotamento_sanitário_adequado": 29.8}, {"Densidade_demográfica": 68.75, "Salário_médio_mensal_dos_trabalhadores_formais": 1.8, "População_ocupada": 6.2, "Taxa_de_escolarização_de_6_a_14_anos_de_idade": 98.2, "Mortalidade_Infantil": 12.05, "Esgotamento_sanitário_adequado": 44.8}, {"Densidade_demográfica": 59.26, "Salário_médio_mensal_dos_trabalhadores_formais": 1.9, "População_ocupada": 6.0, "Taxa_de_escolarização_de_6_a_14_anos_de_idade": 95.6, "Mortalidade_Infantil": 16.27, "Esgotamento_sanitário_adequado": 56.4}, {"Densidade_demográfica": 134.54, "Salário_médio_mensal_dos_trabalhadores_formais": 1.8, "População_ocupada": 5.8, "Taxa_de_escolarização_de_6_a_14_anos_de_idade": 97.4, "Mortalidade_Infantil": 22.99, "Esgotamento_sanitário_adequado": 15.1}, {"Densidade_demográfica": 39.18, "Salário_médio_mensal_dos_trabalhadores_formais": 2.1, "População_ocupada": 4.6, "Taxa_de_escolarização_de_6_a_14_anos_de_idade": 94.7, "Mortalidade_Infantil": 19.81, "Esgotamento_sanitário_adequado": 30.7}, {"Densidade_demográfica": 412.33, "Salário_médio_mensal_dos_trabalhadores_formais": 2.5, "População_ocupada": 19.0, "Taxa_de_escolarização_de_6_a_14_anos_de_idade": 96.5, "Mortalidade_Infantil": 8.41, "Esgotamento_sanitário_adequado": 50.9}, {"Densidade_demográfica": 18.62, "Salário_médio_mensal_dos_trabalhadores_formais": 1.6, "População_ocupada": 9.1, "Taxa_de_escolarização_de_6_a_14_anos_de_idade": 97.6, "Mortalidade_Infantil": 20.72, "Esgotamento_sanitário_adequado": 63.5}, {"Densidade_demográfica": 104.98, "Salário_médio_mensal_dos_trabalhadores_formais": 1.6, "População_ocupada": 7.4, "Taxa_de_escolarização_de_6_a_14_anos_de_idade": 95.3, "Mortalidade_Infantil": 14.81, "Esgotamento_sanitário_adequado": 71.8}, {"Densidade_demográfica": 80.66, "Salário_médio_mensal_dos_trabalhadores_formais": 1.8, "População_ocupada": 7.8, "Taxa_de_escolarização_de_6_a_14_anos_de_idade": 92.6, "Mortalidade_Infantil": 13.45, "Esgotamento_sanitário_adequado": 24.4}, {"Densidade_demográfica": 91.23, "Salário_médio_mensal_dos_trabalhadores_formais": 1.6, "População_ocupada": 3.6, "Taxa_de_escolarização_de_6_a_14_anos_de_idade": 97.1, "Mortalidade_Infantil": 27.21, "Esgotamento_sanitário_adequado": 41.7}, {"Densidade_demográfica": 31.5, "Salário_médio_mensal_dos_trabalhadores_formais": 1.6, "População_ocupada": 6.9, "Taxa_de_escolarização_de_6_a_14_anos_de_idade": 95.3, "Mortalidade_Infantil": 18.69, "Esgotamento_sanitário_adequado": 45.7}, {"Densidade_demográfica": 2818.46, "Salário_médio_mensal_dos_trabalhadores_formais": 1.9, "População_ocupada": 9.4, "Taxa_de_escolarização_de_6_a_14_anos_de_idade": 97.4, "Mortalidade_Infantil": 14.75, "Esgotamento_sanitário_adequado": 40.5}, {"Densidade_demográfica": 235.99, "Salário_médio_mensal_dos_trabalhadores_formais": 1.7, "População_ocupada": 6.6, "Taxa_de_escolarização_de_6_a_14_anos_de_idade": 97.0, "Mortalidade_Infantil": 17.7, "Esgotamento_sanitário_adequado": 76.2}, {"Densidade_demográfica": 217.39, "Salário_médio_mensal_dos_trabalhadores_formais": 2.0, "População_ocupada": 49.0, "Taxa_de_escolarização_de_6_a_14_anos_de_idade": 97.9, "Mortalidade_Infantil": 9.26, "Esgotamento_sanitário_adequado": 29.4}, {"Densidade_demográfica": 57.96, "Salário_médio_mensal_dos_trabalhadores_formais": 1.6, "População_ocupada": 6.4, "Taxa_de_escolarização_de_6_a_14_anos_de_idade": 91.8, "Mortalidade_Infantil": 8.33, "Esgotamento_sanitário_adequado": 54.2}, {"Densidade_demográfica": 58.26, "Salário_médio_mensal_dos_trabalhadores_formais": 1.6, "População_ocupada": 4.9, "Taxa_de_escolarização_de_6_a_14_anos_de_idade": 96.5, "Mortalidade_Infantil": 21.37, "Esgotamento_sanitário_adequado": 31.6}, {"Densidade_demográfica": 43.42, "Salário_médio_mensal_dos_trabalhadores_formais": 1.8, "População_ocupada": 6.0, "Taxa_de_escolarização_de_6_a_14_anos_de_idade": 96.1, "Mortalidade_Infantil": 22.3, "Esgotamento_sanitário_adequado": 41.9}, {"Densidade_demográfica": 11.73, "Salário_médio_mensal_dos_trabalhadores_formais": 1.5, "População_ocupada": 3.2, "Taxa_de_escolarização_de_6_a_14_anos_de_idade": 98.1, "Mortalidade_Infantil": 11.24, "Esgotamento_sanitário_adequado": 14.2}, {"Densidade_demográfica": 516.51, "Salário_médio_mensal_dos_trabalhadores_formais": 1.7, "População_ocupada": 15.2, "Taxa_de_escolarização_de_6_a_14_anos_de_idade": 95.5, "Mortalidade_Infantil": 12.95, "Esgotamento_sanitário_adequado": 15.0}, {"Densidade_demográfica": 342.07, "Salário_médio_mensal_dos_trabalhadores_formais": 1.8, "População_ocupada": 22.6, "Taxa_de_escolarização_de_6_a_14_anos_de_idade": 94.9, "Mortalidade_Infantil": 11.98, "Esgotamento_sanitário_adequado": 81.3}, {"Densidade_demográfica": 118.81, "Salário_médio_mensal_dos_trabalhadores_formais": 1.6, "População_ocupada": 6.8, "Taxa_de_escolarização_de_6_a_14_anos_de_idade": 97.5, "Mortalidade_Infantil": 11.98, "Esgotamento_sanitário_adequado": 11.5}, {"Densidade_demográfica": 182.49, "Salário_médio_mensal_dos_trabalhadores_formais": 1.8, "População_ocupada": 5.2, "Taxa_de_escolarização_de_6_a_14_anos_de_idade": 95.2, "Mortalidade_Infantil": 12.37, "Esgotamento_sanitário_adequado": 61.4}, {"Densidade_demográfica": 72.45, "Salário_médio_mensal_dos_trabalhadores_formais": 1.6, "População_ocupada": 6.8, "Taxa_de_escolarização_de_6_a_14_anos_de_idade": 95.5, "Mortalidade_Infantil": 14.18, "Esgotamento_sanitário_adequado": 53.9}, {"Densidade_demográfica": 255.5, "Salário_médio_mensal_dos_trabalhadores_formais": 1.9, "População_ocupada": 5.6, "Taxa_de_escolarização_de_6_a_14_anos_de_idade": 97.1, "Mortalidade_Infantil": 13.33, "Esgotamento_sanitário_adequado": 19.7}, {"Densidade_demográfica": 237.33, "Salário_médio_mensal_dos_trabalhadores_formais": 1.7, "População_ocupada": 7.3, "Taxa_de_escolarização_de_6_a_14_anos_de_idade": 96.7, "Mortalidade_Infantil": 10.0, "Esgotamento_sanitário_adequado": 45.3}, {"Densidade_demográfica": 270.87, "Salário_médio_mensal_dos_trabalhadores_formais": 1.9, "População_ocupada": 7.0, "Taxa_de_escolarização_de_6_a_14_anos_de_idade": 97.3, "Mortalidade_Infantil": 7.79, "Esgotamento_sanitário_adequado": 3.9}, {"Densidade_demográfica": 53.0, "Salário_médio_mensal_dos_trabalhadores_formais": 1.7, "População_ocupada": 5.6, "Taxa_de_escolarização_de_6_a_14_anos_de_idade": 93.1, "Mortalidade_Infantil": 16.33, "Esgotamento_sanitário_adequado": 48.8}, {"Densidade_demográfica": 122.9, "Salário_médio_mensal_dos_trabalhadores_formais": 1.6, "População_ocupada": 13.8, "Taxa_de_escolarização_de_6_a_14_anos_de_idade": 97.2, "Mortalidade_Infantil": 10.36, "Esgotamento_sanitário_adequado": 55.4}, {"Densidade_demográfica": 58.8, "Salário_médio_mensal_dos_trabalhadores_formais": 1.5, "População_ocupada": 6.7, "Taxa_de_escolarização_de_6_a_14_anos_de_idade": 98.5, "Mortalidade_Infantil": 13.07, "Esgotamento_sanitário_adequado": 20.5}, {"Densidade_demográfica": 221.58, "Salário_médio_mensal_dos_trabalhadores_formais": 1.5, "População_ocupada": 11.1, "Taxa_de_escolarização_de_6_a_14_anos_de_idade": 97.3, "Mortalidade_Infantil": 23.5, "Esgotamento_sanitário_adequado": 79.9}, {"Densidade_demográfica": 24.11, "Salário_médio_mensal_dos_trabalhadores_formais": 2.0, "População_ocupada": 8.8, "Taxa_de_escolarização_de_6_a_14_anos_de_idade": 97.1, "Mortalidade_Infantil": 9.67, "Esgotamento_sanitário_adequado": 52.0}, {"Densidade_demográfica": 11.0, "Salário_médio_mensal_dos_trabalhadores_formais": 1.8, "População_ocupada": 11.0, "Taxa_de_escolarização_de_6_a_14_anos_de_idade": 97.0, "Mortalidade_Infantil": 28.34, "Esgotamento_sanitário_adequado": 70.8}, {"Densidade_demográfica": 183.07, "Salário_médio_mensal_dos_trabalhadores_formais": 1.8, "População_ocupada": 9.5, "Taxa_de_escolarização_de_6_a_14_anos_de_idade": 94.1, "Mortalidade_Infantil": 10.19, "Esgotamento_sanitário_adequado": 37.0}, {"Densidade_demográfica": 23.65, "Salário_médio_mensal_dos_trabalhadores_formais": 1.6, "População_ocupada": 7.0, "Taxa_de_escolarização_de_6_a_14_anos_de_idade": 95.2, "Mortalidade_Infantil": 17.13, "Esgotamento_sanitário_adequado": 16.9}, {"Densidade_demográfica": 190.96, "Salário_médio_mensal_dos_trabalhadores_formais": 1.6, "População_ocupada": 6.9, "Taxa_de_escolarização_de_6_a_14_anos_de_idade": 97.6, "Mortalidade_Infantil": 5.97, "Esgotamento_sanitário_adequado": 21.1}, {"Densidade_demográfica": 154.55, "Salário_médio_mensal_dos_trabalhadores_formais": 2.1, "População_ocupada": 68.2, "Taxa_de_escolarização_de_6_a_14_anos_de_idade": 100.0, "Mortalidade_Infantil": 38.46, "Esgotamento_sanitário_adequado": 82.7}, {"Densidade_demográfica": 127.93, "Salário_médio_mensal_dos_trabalhadores_formais": 1.5, "População_ocupada": 6.8, "Taxa_de_escolarização_de_6_a_14_anos_de_idade": 97.9, "Mortalidade_Infantil": 6.8, "Esgotamento_sanitário_adequado": 49.3}, {"Densidade_demográfica": 22.27, "Salário_médio_mensal_dos_trabalhadores_formais": 1.4, "População_ocupada": 6.1, "Taxa_de_escolarização_de_6_a_14_anos_de_idade": 96.4, "Mortalidade_Infantil": 15.27, "Esgotamento_sanitário_adequado": 31.9}, {"Densidade_demográfica": 8.04, "Salário_médio_mensal_dos_trabalhadores_formais": 1.7, "População_ocupada": 13.0, "Taxa_de_escolarização_de_6_a_14_anos_de_idade": 95.6, "Mortalidade_Infantil": 21.93, "Esgotamento_sanitário_adequado": 40.3}, {"Densidade_demográfica": 67.2, "Salário_médio_mensal_dos_trabalhadores_formais": 1.7, "População_ocupada": 5.8, "Taxa_de_escolarização_de_6_a_14_anos_de_idade": 95.4, "Mortalidade_Infantil": 14.29, "Esgotamento_sanitário_adequado": 13.9}, {"Densidade_demográfica": 109.05, "Salário_médio_mensal_dos_trabalhadores_formais": 1.7, "População_ocupada": 4.1, "Taxa_de_escolarização_de_6_a_14_anos_de_idade": 97.0, "Mortalidade_Infantil": 11.2, "Esgotamento_sanitário_adequado": 54.3}, {"Densidade_demográfica": 282.21, "Salário_médio_mensal_dos_trabalhadores_formais": 1.8, "População_ocupada": 16.1, "Taxa_de_escolarização_de_6_a_14_anos_de_idade": 96.8, "Mortalidade_Infantil": 13.79, "Esgotamento_sanitário_adequado": 52.1}, {"Densidade_demográfica": 125.17, "Salário_médio_mensal_dos_trabalhadores_formais": 2.0, "População_ocupada": 9.0, "Taxa_de_escolarização_de_6_a_14_anos_de_idade": 98.3, "Mortalidade_Infantil": 9.01, "Esgotamento_sanitário_adequado": 34.2}, {"Densidade_demográfica": 150.72, "Salário_médio_mensal_dos_trabalhadores_formais": 2.5, "População_ocupada": 28.9, "Taxa_de_escolarização_de_6_a_14_anos_de_idade": 96.7, "Mortalidade_Infantil": 10.14, "Esgotamento_sanitário_adequado": 33.5}, {"Densidade_demográfica": 13.13, "Salário_médio_mensal_dos_trabalhadores_formais": 1.8, "População_ocupada": 6.8, "Taxa_de_escolarização_de_6_a_14_anos_de_idade": 98.5, "Mortalidade_Infantil": 10.53, "Esgotamento_sanitário_adequado": 29.8}, {"Densidade_demográfica": 150.87, "Salário_médio_mensal_dos_trabalhadores_formais": 1.6, "População_ocupada": 13.4, "Taxa_de_escolarização_de_6_a_14_anos_de_idade": 97.2, "Mortalidade_Infantil": 3.82, "Esgotamento_sanitário_adequado": 65.0}, {"Densidade_demográfica": 28.91, "Salário_médio_mensal_dos_trabalhadores_formais": 1.9, "População_ocupada": 6.2, "Taxa_de_escolarização_de_6_a_14_anos_de_idade": 90.5, "Mortalidade_Infantil": 7.19, "Esgotamento_sanitário_adequado": 35.5}, {"Densidade_demográfica": 14.14, "Salário_médio_mensal_dos_trabalhadores_formais": 1.6, "População_ocupada": 4.8, "Taxa_de_escolarização_de_6_a_14_anos_de_idade": 93.7, "Mortalidade_Infantil": 10.33, "Esgotamento_sanitário_adequado": 33.6}, {"Densidade_demográfica": 39.74, "Salário_médio_mensal_dos_trabalhadores_formais": 1.6, "População_ocupada": 4.7, "Taxa_de_escolarização_de_6_a_14_anos_de_idade": 96.7, "Mortalidade_Infantil": 19.61, "Esgotamento_sanitário_adequado": 45.8}, {"Densidade_demográfica": 333.88, "Salário_médio_mensal_dos_trabalhadores_formais": 2.1, "População_ocupada": 17.6, "Taxa_de_escolarização_de_6_a_14_anos_de_idade": 97.9, "Mortalidade_Infantil": 15.54, "Esgotamento_sanitário_adequado": 19.9}, {"Densidade_demográfica": 14.05, "Salário_médio_mensal_dos_trabalhadores_formais": 1.8, "População_ocupada": 4.5, "Taxa_de_escolarização_de_6_a_14_anos_de_idade": 98.7, "Mortalidade_Infantil": 6.67, "Esgotamento_sanitário_adequado": 36.3}, {"Densidade_demográfica": 16.14, "Salário_médio_mensal_dos_trabalhadores_formais": 1.7, "População_ocupada": 6.3, "Taxa_de_escolarização_de_6_a_14_anos_de_idade": 84.2, "Mortalidade_Infantil": 18.13, "Esgotamento_sanitário_adequado": 23.0}, {"Densidade_demográfica": 18.45, "Salário_médio_mensal_dos_trabalhadores_formais": 1.7, "População_ocupada": 7.6, "Taxa_de_escolarização_de_6_a_14_anos_de_idade": 98.2, "Mortalidade_Infantil": 15.38, "Esgotamento_sanitário_adequado": 42.9}, {"Densidade_demográfica": 152.98, "Salário_médio_mensal_dos_trabalhadores_formais": 3.4, "População_ocupada": 37.1, "Taxa_de_escolarização_de_6_a_14_anos_de_idade": 97.3, "Mortalidade_Infantil": 12.05, "Esgotamento_sanitário_adequado": 50.6}, {"Densidade_demográfica": 32.64, "Salário_médio_mensal_dos_trabalhadores_formais": 1.6, "População_ocupada": 7.7, "Taxa_de_escolarização_de_6_a_14_anos_de_idade": 95.1, "Mortalidade_Infantil": 18.37, "Esgotamento_sanitário_adequado": 20.9}, {"Densidade_demográfica": 10.16, "Salário_médio_mensal_dos_trabalhadores_formais": 1.8, "População_ocupada": 15.3, "Taxa_de_escolarização_de_6_a_14_anos_de_idade": 97.5, "Mortalidade_Infantil": 12.99, "Esgotamento_sanitário_adequado": 82.2}, {"Densidade_demográfica": 24.2, "Salário_médio_mensal_dos_trabalhadores_formais": 2.0, "População_ocupada": 4.2, "Taxa_de_escolarização_de_6_a_14_anos_de_idade": 93.3, "Mortalidade_Infantil": 11.76, "Esgotamento_sanitário_adequado": 31.2}, {"Densidade_demográfica": 328.17, "Salário_médio_mensal_dos_trabalhadores_formais": 1.8, "População_ocupada": 7.0, "Taxa_de_escolarização_de_6_a_14_anos_de_idade": 97.6, "Mortalidade_Infantil": 9.06, "Esgotamento_sanitário_adequado": 20.5}, {"Densidade_demográfica": 116.13, "Salário_médio_mensal_dos_trabalhadores_formais": 1.5, "População_ocupada": 9.2, "Taxa_de_escolarização_de_6_a_14_anos_de_idade": 94.6, "Mortalidade_Infantil": 4.89, "Esgotamento_sanitário_adequado": 18.4}, {"Densidade_demográfica": 34.29, "Salário_médio_mensal_dos_trabalhadores_formais": 1.6, "População_ocupada": 7.6, "Taxa_de_escolarização_de_6_a_14_anos_de_idade": 97.5, "Mortalidade_Infantil": 5.99, "Esgotamento_sanitário_adequado": 51.5}, {"Densidade_demográfica": 320.19, "Salário_médio_mensal_dos_trabalhadores_formais": 3.1, "População_ocupada": 20.9, "Taxa_de_escolarização_de_6_a_14_anos_de_idade": 97.6, "Mortalidade_Infantil": 3.09, "Esgotamento_sanitário_adequado": 25.0}, {"Densidade_demográfica": 151.72, "Salário_médio_mensal_dos_trabalhadores_formais": 1.7, "População_ocupada": 4.8, "Taxa_de_escolarização_de_6_a_14_anos_de_idade": 97.3, "Mortalidade_Infantil": 8.26, "Esgotamento_sanitário_adequado": 9.5}, {"Densidade_demográfica": 2491.82, "Salário_médio_mensal_dos_trabalhadores_formais": 2.1, "População_ocupada": 15.6, "Taxa_de_escolarização_de_6_a_14_anos_de_idade": 96.8, "Mortalidade_Infantil": 10.63, "Esgotamento_sanitário_adequado": 45.4}, {"Densidade_demográfica": 131.88, "Salário_médio_mensal_dos_trabalhadores_formais": 1.8, "População_ocupada": 6.8, "Taxa_de_escolarização_de_6_a_14_anos_de_idade": 95.4, "Mortalidade_Infantil": 8.4, "Esgotamento_sanitário_adequado": 33.1}, {"Densidade_demográfica": 23.53, "Salário_médio_mensal_dos_trabalhadores_formais": 1.5, "População_ocupada": 6.9, "Taxa_de_escolarização_de_6_a_14_anos_de_idade": 97.6, "Mortalidade_Infantil": 16.53, "Esgotamento_sanitário_adequado": 55.9}, {"Densidade_demográfica": 50.25, "Salário_médio_mensal_dos_trabalhadores_formais": 1.7, "População_ocupada": 9.5, "Taxa_de_escolarização_de_6_a_14_anos_de_idade": 97.7, "Mortalidade_Infantil": 22.42, "Esgotamento_sanitário_adequado": 68.0}, {"Densidade_demográfica": 227.52, "Salário_médio_mensal_dos_trabalhadores_formais": 1.6, "População_ocupada": 6.8, "Taxa_de_escolarização_de_6_a_14_anos_de_idade": 97.1, "Mortalidade_Infantil": 11.33, "Esgotamento_sanitário_adequado": 17.3}, {"Densidade_demográfica": 129.39, "Salário_médio_mensal_dos_trabalhadores_formais": 1.9, "População_ocupada": 8.6, "Taxa_de_escolarização_de_6_a_14_anos_de_idade": 95.5, "Mortalidade_Infantil": 3.56, "Esgotamento_sanitário_adequado": 49.9}, {"Densidade_demográfica": 87.92, "Salário_médio_mensal_dos_trabalhadores_formais": 1.7, "População_ocupada": 6.8, "Taxa_de_escolarização_de_6_a_14_anos_de_idade": 98.0, "Mortalidade_Infantil": 34.48, "Esgotamento_sanitário_adequado": 48.3}, {"Densidade_demográfica": 130.53, "Salário_médio_mensal_dos_trabalhadores_formais": 1.7, "População_ocupada": 7.9, "Taxa_de_escolarização_de_6_a_14_anos_de_idade": 96.3, "Mortalidade_Infantil": 14.34, "Esgotamento_sanitário_adequado": 50.5}, {"Densidade_demográfica": 98.08, "Salário_médio_mensal_dos_trabalhadores_formais": 1.7, "População_ocupada": 4.8, "Taxa_de_escolarização_de_6_a_14_anos_de_idade": 96.0, "Mortalidade_Infantil": 23.04, "Esgotamento_sanitário_adequado": 61.7}, {"Densidade_demográfica": 229.77, "Salário_médio_mensal_dos_trabalhadores_formais": 1.7, "População_ocupada": 8.2, "Taxa_de_escolarização_de_6_a_14_anos_de_idade": 97.8, "Mortalidade_Infantil": 12.88, "Esgotamento_sanitário_adequado": 9.8}, {"Densidade_demográfica": 360.65, "Salário_médio_mensal_dos_trabalhadores_formais": 1.7, "População_ocupada": 29.1, "Taxa_de_escolarização_de_6_a_14_anos_de_idade": 98.9, "Mortalidade_Infantil": 8.65, "Esgotamento_sanitário_adequado": 14.5}, {"Densidade_demográfica": 61.04, "Salário_médio_mensal_dos_trabalhadores_formais": 1.5, "População_ocupada": 6.1, "Taxa_de_escolarização_de_6_a_14_anos_de_idade": 96.5, "Mortalidade_Infantil": 25.91, "Esgotamento_sanitário_adequado": 52.3}, {"Densidade_demográfica": 70.06, "Salário_médio_mensal_dos_trabalhadores_formais": 2.0, "População_ocupada": 3.6, "Taxa_de_escolarização_de_6_a_14_anos_de_idade": 96.5, "Mortalidade_Infantil": 9.09, "Esgotamento_sanitário_adequado": 45.0}, {"Densidade_demográfica": 12.31, "Salário_médio_mensal_dos_trabalhadores_formais": 1.4, "População_ocupada": 12.8, "Taxa_de_escolarização_de_6_a_14_anos_de_idade": 96.3, "Mortalidade_Infantil": 10.81, "Esgotamento_sanitário_adequado": 40.4}, {"Densidade_demográfica": 193.7, "Salário_médio_mensal_dos_trabalhadores_formais": 1.5, "População_ocupada": 10.9, "Taxa_de_escolarização_de_6_a_14_anos_de_idade": 97.9, "Mortalidade_Infantil": 17.24, "Esgotamento_sanitário_adequado": 63.9}, {"Densidade_demográfica": 202.53, "Salário_médio_mensal_dos_trabalhadores_formais": 1.7, "População_ocupada": 14.0, "Taxa_de_escolarização_de_6_a_14_anos_de_idade": 98.0, "Mortalidade_Infantil": 7.68, "Esgotamento_sanitário_adequado": 44.8}, {"Densidade_demográfica": 221.43, "Salário_médio_mensal_dos_trabalhadores_formais": 1.6, "População_ocupada": 8.3, "Taxa_de_escolarização_de_6_a_14_anos_de_idade": 97.9, "Mortalidade_Infantil": 5.24, "Esgotamento_sanitário_adequado": 59.4}, {"Densidade_demográfica": 226.46, "Salário_médio_mensal_dos_trabalhadores_formais": 1.5, "População_ocupada": 7.6, "Taxa_de_escolarização_de_6_a_14_anos_de_idade": 82.9, "Mortalidade_Infantil": 4.72, "Esgotamento_sanitário_adequado": 23.8}, {"Densidade_demográfica": 47.56, "Salário_médio_mensal_dos_trabalhadores_formais": 1.9, "População_ocupada": 3.5, "Taxa_de_escolarização_de_6_a_14_anos_de_idade": 93.4, "Mortalidade_Infantil": 12.1, "Esgotamento_sanitário_adequado": 5.6}, {"Densidade_demográfica": 61.19, "Salário_médio_mensal_dos_trabalhadores_formais": 1.3, "População_ocupada": 11.3, "Taxa_de_escolarização_de_6_a_14_anos_de_idade": 94.1, "Mortalidade_Infantil": 4.17, "Esgotamento_sanitário_adequado": 22.3}, {"Densidade_demográfica": 17.41, "Salário_médio_mensal_dos_trabalhadores_formais": 1.8, "População_ocupada": 5.1, "Taxa_de_escolarização_de_6_a_14_anos_de_idade": 95.8, "Mortalidade_Infantil": 12.2, "Esgotamento_sanitário_adequado": 54.2}, {"Densidade_demográfica": 289.16, "Salário_médio_mensal_dos_trabalhadores_formais": 1.9, "População_ocupada": 10.2, "Taxa_de_escolarização_de_6_a_14_anos_de_idade": 95.8, "Mortalidade_Infantil": 15.83, "Esgotamento_sanitário_adequado": 52.3}, {"Densidade_demográfica": 204.95, "Salário_médio_mensal_dos_trabalhadores_formais": 1.6, "População_ocupada": 15.6, "Taxa_de_escolarização_de_6_a_14_anos_de_idade": 96.1, "Mortalidade_Infantil": 16.13, "Esgotamento_sanitário_adequado": 77.7}, {"Densidade_demográfica": 9063.58, "Salário_médio_mensal_dos_trabalhadores_formais": 1.8, "População_ocupada": 21.1, "Taxa_de_escolarização_de_6_a_14_anos_de_idade": 96.9, "Mortalidade_Infantil": 10.23, "Esgotamento_sanitário_adequado": 56.6}, {"Densidade_demográfica": 164.99, "Salário_médio_mensal_dos_trabalhadores_formais": 1.7, "População_ocupada": 7.0, "Taxa_de_escolarização_de_6_a_14_anos_de_idade": 97.2, "Mortalidade_Infantil": 3.8, "Esgotamento_sanitário_adequado": 20.3}, {"Densidade_demográfica": 23.76, "Salário_médio_mensal_dos_trabalhadores_formais": 1.9, "População_ocupada": 6.2, "Taxa_de_escolarização_de_6_a_14_anos_de_idade": 98.0, "Mortalidade_Infantil": 17.73, "Esgotamento_sanitário_adequado": 36.9}, {"Densidade_demográfica": 26.56, "Salário_médio_mensal_dos_trabalhadores_formais": 1.9, "População_ocupada": 7.2, "Taxa_de_escolarização_de_6_a_14_anos_de_idade": 92.4, "Mortalidade_Infantil": 11.97, "Esgotamento_sanitário_adequado": 58.3}, {"Densidade_demográfica": 175.44, "Salário_médio_mensal_dos_trabalhadores_formais": 1.8, "População_ocupada": 11.4, "Taxa_de_escolarização_de_6_a_14_anos_de_idade": 96.3, "Mortalidade_Infantil": 15.04, "Esgotamento_sanitário_adequado": 55.9}, {"Densidade_demográfica": 51.82, "Salário_médio_mensal_dos_trabalhadores_formais": 1.8, "População_ocupada": 5.3, "Taxa_de_escolarização_de_6_a_14_anos_de_idade": 94.0, "Mortalidade_Infantil": 27.27, "Esgotamento_sanitário_adequado": 51.0}, {"Densidade_demográfica": 69.14, "Salário_médio_mensal_dos_trabalhadores_formais": 1.4, "População_ocupada": 7.5, "Taxa_de_escolarização_de_6_a_14_anos_de_idade": 98.6, "Mortalidade_Infantil": 13.89, "Esgotamento_sanitário_adequado": 55.0}, {"Densidade_demográfica": 47.65, "Salário_médio_mensal_dos_trabalhadores_formais": 1.5, "População_ocupada": 6.7, "Taxa_de_escolarização_de_6_a_14_anos_de_idade": 97.9, "Mortalidade_Infantil": 4.65, "Esgotamento_sanitário_adequado": 4.6}, {"Densidade_demográfica": 7.79, "Salário_médio_mensal_dos_trabalhadores_formais": 1.2, "População_ocupada": 8.2, "Taxa_de_escolarização_de_6_a_14_anos_de_idade": 97.0, "Mortalidade_Infantil": 18.8, "Esgotamento_sanitário_adequado": 33.9}, {"Densidade_demográfica": 87.61, "Salário_médio_mensal_dos_trabalhadores_formais": 1.6, "População_ocupada": 6.1, "Taxa_de_escolarização_de_6_a_14_anos_de_idade": 95.9, "Mortalidade_Infantil": 10.36, "Esgotamento_sanitário_adequado": 17.3}, {"Densidade_demográfica": 185.06, "Salário_médio_mensal_dos_trabalhadores_formais": 1.6, "População_ocupada": 7.9, "Taxa_de_escolarização_de_6_a_14_anos_de_idade": 96.7, "Mortalidade_Infantil": 13.55, "Esgotamento_sanitário_adequado": 31.5}, {"Densidade_demográfica": 3087.66, "Salário_médio_mensal_dos_trabalhadores_formais": 1.9, "População_ocupada": 10.8, "Taxa_de_escolarização_de_6_a_14_anos_de_idade": 97.9, "Mortalidade_Infantil": 12.61, "Esgotamento_sanitário_adequado": 60.8}, {"Densidade_demográfica": 26.08, "Salário_médio_mensal_dos_trabalhadores_formais": 1.7, "População_ocupada": 4.3, "Taxa_de_escolarização_de_6_a_14_anos_de_idade": 92.0, "Mortalidade_Infantil": 14.29, "Esgotamento_sanitário_adequado": 41.4}, {"Densidade_demográfica": 63.21, "Salário_médio_mensal_dos_trabalhadores_formais": 1.7, "População_ocupada": 8.8, "Taxa_de_escolarização_de_6_a_14_anos_de_idade": 97.4, "Mortalidade_Infantil": 8.19, "Esgotamento_sanitário_adequado": 60.8}, {"Densidade_demográfica": 30.75, "Salário_médio_mensal_dos_trabalhadores_formais": 2.2, "População_ocupada": 12.9, "Taxa_de_escolarização_de_6_a_14_anos_de_idade": 96.0, "Mortalidade_Infantil": 7.79, "Esgotamento_sanitário_adequado": 69.7}, {"Densidade_demográfica": 64.44, "Salário_médio_mensal_dos_trabalhadores_formais": 2.2, "População_ocupada": 20.1, "Taxa_de_escolarização_de_6_a_14_anos_de_idade": 97.0, "Mortalidade_Infantil": 15.3, "Esgotamento_sanitário_adequado": 72.7}, {"Densidade_demográfica": 45.56, "Salário_médio_mensal_dos_trabalhadores_formais": 1.6, "População_ocupada": 8.5, "Taxa_de_escolarização_de_6_a_14_anos_de_idade": 97.0, "Mortalidade_Infantil": 21.9, "Esgotamento_sanitário_adequado": 43.8}, {"Densidade_demográfica": 118.35, "Salário_médio_mensal_dos_trabalhadores_formais": 1.7, "População_ocupada": 10.3, "Taxa_de_escolarização_de_6_a_14_anos_de_idade": 95.0, "Mortalidade_Infantil": 17.86, "Esgotamento_sanitário_adequado": 66.1}, {"Densidade_demográfica": 121.97, "Salário_médio_mensal_dos_trabalhadores_formais": 1.6, "População_ocupada": 6.2, "Taxa_de_escolarização_de_6_a_14_anos_de_idade": 96.7, "Mortalidade_Infantil": 6.8, "Esgotamento_sanitário_adequado": 44.9}, {"Densidade_demográfica": 104.88, "Salário_médio_mensal_dos_trabalhadores_formais": 1.7, "População_ocupada": 5.3, "Taxa_de_escolarização_de_6_a_14_anos_de_idade": 97.2, "Mortalidade_Infantil": 10.56, "Esgotamento_sanitário_adequado": 47.4}, {"Densidade_demográfica": 31.98, "Salário_médio_mensal_dos_trabalhadores_formais": 1.7, "População_ocupada": 5.8, "Taxa_de_escolarização_de_6_a_14_anos_de_idade": 99.2, "Mortalidade_Infantil": 11.49, "Esgotamento_sanitário_adequado": 28.0}, {"Densidade_demográfica": 7039.64, "Salário_médio_mensal_dos_trabalhadores_formais": 3.3, "População_ocupada": 43.1, "Taxa_de_escolarização_de_6_a_14_anos_de_idade": 97.1, "Mortalidade_Infantil": 10.83, "Esgotamento_sanitário_adequado": 69.2}, {"Densidade_demográfica": 61.02, "Salário_médio_mensal_dos_trabalhadores_formais": 1.7, "População_ocupada": 7.3, "Taxa_de_escolarização_de_6_a_14_anos_de_idade": 93.4, "Mortalidade_Infantil": 9.55, "Esgotamento_sanitário_adequado": 49.4}, {"Densidade_demográfica": 154.35, "Salário_médio_mensal_dos_trabalhadores_formais": 1.8, "População_ocupada": 8.2, "Taxa_de_escolarização_de_6_a_14_anos_de_idade": 92.9, "Mortalidade_Infantil": 11.29, "Esgotamento_sanitário_adequado": 64.8}, {"Densidade_demográfica": 97.39, "Salário_médio_mensal_dos_trabalhadores_formais": 1.6, "População_ocupada": 33.1, "Taxa_de_escolarização_de_6_a_14_anos_de_idade": 89.5, "Mortalidade_Infantil": 14.88, "Esgotamento_sanitário_adequado": 32.5}, {"Densidade_demográfica": 59.36, "Salário_médio_mensal_dos_trabalhadores_formais": 1.8, "População_ocupada": 11.2, "Taxa_de_escolarização_de_6_a_14_anos_de_idade": 97.7, "Mortalidade_Infantil": 8.7, "Esgotamento_sanitário_adequado": 30.1}, {"Densidade_demográfica": 106.77, "Salário_médio_mensal_dos_trabalhadores_formais": 1.8, "População_ocupada": 5.2, "Taxa_de_escolarização_de_6_a_14_anos_de_idade": 87.6, "Mortalidade_Infantil": 27.78, "Esgotamento_sanitário_adequado": 14.4}, {"Densidade_demográfica": 33.57, "Salário_médio_mensal_dos_trabalhadores_formais": 1.9, "População_ocupada": 12.6, "Taxa_de_escolarização_de_6_a_14_anos_de_idade": 96.7, "Mortalidade_Infantil": 15.2, "Esgotamento_sanitário_adequado": 62.8}, {"Densidade_demográfica": 60.73, "Salário_médio_mensal_dos_trabalhadores_formais": 1.6, "População_ocupada": 4.5, "Taxa_de_escolarização_de_6_a_14_anos_de_idade": 97.4, "Mortalidade_Infantil": 13.64, "Esgotamento_sanitário_adequado": 36.4}, {"Densidade_demográfica": 81.71, "Salário_médio_mensal_dos_trabalhadores_formais": 1.7, "População_ocupada": 5.2, "Taxa_de_escolarização_de_6_a_14_anos_de_idade": 93.2, "Mortalidade_Infantil": 17.54, "Esgotamento_sanitário_adequado": 50.0}, {"Densidade_demográfica": 10.82, "Salário_médio_mensal_dos_trabalhadores_formais": 1.7, "População_ocupada": 4.6, "Taxa_de_escolarização_de_6_a_14_anos_de_idade": 97.5, "Mortalidade_Infantil": 25.0, "Esgotamento_sanitário_adequado": 25.3}, {"Densidade_demográfica": 102.39, "Salário_médio_mensal_dos_trabalhadores_formais": 1.7, "População_ocupada": 8.1, "Taxa_de_escolarização_de_6_a_14_anos_de_idade": 97.8, "Mortalidade_Infantil": 26.46, "Esgotamento_sanitário_adequado": 43.4}, {"Densidade_demográfica": 261.2, "Salário_médio_mensal_dos_trabalhadores_formais": 1.5, "População_ocupada": 15.0, "Taxa_de_escolarização_de_6_a_14_anos_de_idade": 95.7, "Mortalidade_Infantil": 16.86, "Esgotamento_sanitário_adequado": 87.6}, {"Densidade_demográfica": 13.3, "Salário_médio_mensal_dos_trabalhadores_formais": 1.7, "População_ocupada": 5.5, "Taxa_de_escolarização_de_6_a_14_anos_de_idade": 97.0, "Mortalidade_Infantil": 17.96, "Esgotamento_sanitário_adequado": 8.6}, {"Densidade_demográfica": 13.14, "Salário_médio_mensal_dos_trabalhadores_formais": 2.2, "População_ocupada": 5.7, "Taxa_de_escolarização_de_6_a_14_anos_de_idade": 97.4, "Mortalidade_Infantil": 8.76, "Esgotamento_sanitário_adequado": 40.1}, {"Densidade_demográfica": 141.31, "Salário_médio_mensal_dos_trabalhadores_formais": 1.9, "População_ocupada": 5.5, "Taxa_de_escolarização_de_6_a_14_anos_de_idade": 96.4, "Mortalidade_Infantil": 14.71, "Esgotamento_sanitário_adequado": 23.2}, {"Densidade_demográfica": 56.2, "Salário_médio_mensal_dos_trabalhadores_formais": 1.5, "População_ocupada": 7.7, "Taxa_de_escolarização_de_6_a_14_anos_de_idade": 97.8, "Mortalidade_Infantil": 12.2, "Esgotamento_sanitário_adequado": 49.5}, {"Densidade_demográfica": 86.87, "Salário_médio_mensal_dos_trabalhadores_formais": 1.7, "População_ocupada": 5.2, "Taxa_de_escolarização_de_6_a_14_anos_de_idade": 83.7, "Mortalidade_Infantil": 11.49, "Esgotamento_sanitário_adequado": 23.9}, {"Densidade_demográfica": 74.03, "Salário_médio_mensal_dos_trabalhadores_formais": 1.7, "População_ocupada": 8.3, "Taxa_de_escolarização_de_6_a_14_anos_de_idade": 93.0, "Mortalidade_Infantil": 8.45, "Esgotamento_sanitário_adequado": 45.7}, {"Densidade_demográfica": 92.23, "Salário_médio_mensal_dos_trabalhadores_formais": 1.6, "População_ocupada": 8.8, "Taxa_de_escolarização_de_6_a_14_anos_de_idade": 97.2, "Mortalidade_Infantil": 9.12, "Esgotamento_sanitário_adequado": 50.2}, {"Densidade_demográfica": 82.5, "Salário_médio_mensal_dos_trabalhadores_formais": 1.5, "População_ocupada": 6.3, "Taxa_de_escolarização_de_6_a_14_anos_de_idade": 96.3, "Mortalidade_Infantil": 12.99, "Esgotamento_sanitário_adequado": 25.7}, {"Densidade_demográfica": 88.39, "Salário_médio_mensal_dos_trabalhadores_formais": 1.7, "População_ocupada": 4.5, "Taxa_de_escolarização_de_6_a_14_anos_de_idade": 94.2, "Mortalidade_Infantil": 3.26, "Esgotamento_sanitário_adequado": 64.7}, {"Densidade_demográfica": 262.19, "Salário_médio_mensal_dos_trabalhadores_formais": 1.6, "População_ocupada": 8.5, "Taxa_de_escolarização_de_6_a_14_anos_de_idade": 95.8, "Mortalidade_Infantil": 11.9, "Esgotamento_sanitário_adequado": 4.3}, {"Densidade_demográfica": 22.13, "Salário_médio_mensal_dos_trabalhadores_formais": 1.7, "População_ocupada": 7.9, "Taxa_de_escolarização_de_6_a_14_anos_de_idade": 96.2, "Mortalidade_Infantil": 9.03, "Esgotamento_sanitário_adequado": 33.9}, {"Densidade_demográfica": 39.84, "Salário_médio_mensal_dos_trabalhadores_formais": 1.7, "População_ocupada": 8.9, "Taxa_de_escolarização_de_6_a_14_anos_de_idade": 98.9, "Mortalidade_Infantil": 6.54, "Esgotamento_sanitário_adequado": 63.2}, {"Densidade_demográfica": 392.57, "Salário_médio_mensal_dos_trabalhadores_formais": 2.0, "População_ocupada": 9.7, "Taxa_de_escolarização_de_6_a_14_anos_de_idade": 97.1, "Mortalidade_Infantil": 10.63, "Esgotamento_sanitário_adequado": 38.4}, {"Densidade_demográfica": 149.14, "Salário_médio_mensal_dos_trabalhadores_formais": 1.8, "População_ocupada": 6.7, "Taxa_de_escolarização_de_6_a_14_anos_de_idade": 95.2, "Mortalidade_Infantil": 7.52, "Esgotamento_sanitário_adequado": 55.8}, {"Densidade_demográfica": 26.59, "Salário_médio_mensal_dos_trabalhadores_formais": 1.7, "População_ocupada": 14.1, "Taxa_de_escolarização_de_6_a_14_anos_de_idade": 96.7, "Mortalidade_Infantil": 12.72, "Esgotamento_sanitário_adequado": 70.2}, {"Densidade_demográfica": 11.92, "Salário_médio_mensal_dos_trabalhadores_formais": 1.4, "População_ocupada": 5.4, "Taxa_de_escolarização_de_6_a_14_anos_de_idade": 98.1, "Mortalidade_Infantil": 32.26, "Esgotamento_sanitário_adequado": 34.4}, {"Densidade_demográfica": 13.95, "Salário_médio_mensal_dos_trabalhadores_formais": 1.9, "População_ocupada": 12.7, "Taxa_de_escolarização_de_6_a_14_anos_de_idade": 94.6, "Mortalidade_Infantil": 10.03, "Esgotamento_sanitário_adequado": 56.3}, {"Densidade_demográfica": 107.57, "Salário_médio_mensal_dos_trabalhadores_formais": 1.8, "População_ocupada": 19.3, "Taxa_de_escolarização_de_6_a_14_anos_de_idade": 94.1, "Mortalidade_Infantil": 17.45, "Esgotamento_sanitário_adequado": 33.4}, {"Densidade_demográfica": 27.52, "Salário_médio_mensal_dos_trabalhadores_formais": 1.6, "População_ocupada": 7.2, "Taxa_de_escolarização_de_6_a_14_anos_de_idade": 96.8, "Mortalidade_Infantil": 14.49, "Esgotamento_sanitário_adequado": 11.2}, {"Densidade_demográfica": 41.5, "Salário_médio_mensal_dos_trabalhadores_formais": 1.5, "População_ocupada": 7.4, "Taxa_de_escolarização_de_6_a_14_anos_de_idade": 96.9, "Mortalidade_Infantil": 11.36, "Esgotamento_sanitário_adequado": 36.4}, {"Densidade_demográfica": 231.42, "Salário_médio_mensal_dos_trabalhadores_formais": 1.7, "População_ocupada": 10.9, "Taxa_de_escolarização_de_6_a_14_anos_de_idade": 97.8, "Mortalidade_Infantil": 9.48, "Esgotamento_sanitário_adequado": 58.0}, {"Densidade_demográfica": 68.11, "Salário_médio_mensal_dos_trabalhadores_formais": 1.7, "População_ocupada": 7.9, "Taxa_de_escolarização_de_6_a_14_anos_de_idade": 97.2, "Mortalidade_Infantil": 7.54, "Esgotamento_sanitário_adequado": 70.7}, {"Densidade_demográfica": 55.91, "Salário_médio_mensal_dos_trabalhadores_formais": 1.6, "População_ocupada": 6.9, "Taxa_de_escolarização_de_6_a_14_anos_de_idade": 94.4, "Mortalidade_Infantil": 20.13, "Esgotamento_sanitário_adequado": 53.6}, {"Densidade_demográfica": 17.45, "Salário_médio_mensal_dos_trabalhadores_formais": 1.6, "População_ocupada": 5.6, "Taxa_de_escolarização_de_6_a_14_anos_de_idade": 96.3, "Mortalidade_Infantil": 19.23, "Esgotamento_sanitário_adequado": 21.2}, {"Densidade_demográfica": 96.66, "Salário_médio_mensal_dos_trabalhadores_formais": 1.5, "População_ocupada": 15.3, "Taxa_de_escolarização_de_6_a_14_anos_de_idade": 95.5, "Mortalidade_Infantil": 22.56, "Esgotamento_sanitário_adequado": 17.9}, {"Densidade_demográfica": 52.41, "Salário_médio_mensal_dos_trabalhadores_formais": 1.5, "População_ocupada": 8.2, "Taxa_de_escolarização_de_6_a_14_anos_de_idade": 96.2, "Mortalidade_Infantil": 10.96, "Esgotamento_sanitário_adequado": 43.1}, {"Densidade_demográfica": 44.48, "Salário_médio_mensal_dos_trabalhadores_formais": 1.7, "População_ocupada": 5.0, "Taxa_de_escolarização_de_6_a_14_anos_de_idade": 95.7, "Mortalidade_Infantil": 29.13, "Esgotamento_sanitário_adequado": 56.3}, {"Densidade_demográfica": 28.95, "Salário_médio_mensal_dos_trabalhadores_formais": 1.7, "População_ocupada": 5.6, "Taxa_de_escolarização_de_6_a_14_anos_de_idade": 98.2, "Mortalidade_Infantil": 8.06, "Esgotamento_sanitário_adequado": 46.9}, {"Densidade_demográfica": 184.63, "Salário_médio_mensal_dos_trabalhadores_formais": 1.7, "População_ocupada": 14.4, "Taxa_de_escolarização_de_6_a_14_anos_de_idade": 97.7, "Mortalidade_Infantil": 5.26, "Esgotamento_sanitário_adequado": 66.2}, {"Densidade_demográfica": 1383.21, "Salário_médio_mensal_dos_trabalhadores_formais": 1.5, "População_ocupada": 15.2, "Taxa_de_escolarização_de_6_a_14_anos_de_idade": 91.5, "Mortalidade_Infantil": 13.2, "Esgotamento_sanitário_adequado": 79.5}, {"Densidade_demográfica": 110.27, "Salário_médio_mensal_dos_trabalhadores_formais": 1.6, "População_ocupada": 5.9, "Taxa_de_escolarização_de_6_a_14_anos_de_idade": 97.0, "Mortalidade_Infantil": 11.24, "Esgotamento_sanitário_adequado": 24.9}, {"Densidade_demográfica": 113.77, "Salário_médio_mensal_dos_trabalhadores_formais": 1.7, "População_ocupada": 8.8, "Taxa_de_escolarização_de_6_a_14_anos_de_idade": 97.9, "Mortalidade_Infantil": 15.2, "Esgotamento_sanitário_adequado": 42.4}, {"Densidade_demográfica": 78.35, "Salário_médio_mensal_dos_trabalhadores_formais": 1.7, "População_ocupada": 12.6, "Taxa_de_escolarização_de_6_a_14_anos_de_idade": 98.4, "Mortalidade_Infantil": 9.85, "Esgotamento_sanitário_adequado": 19.8}, {"Densidade_demográfica": 25.7, "Salário_médio_mensal_dos_trabalhadores_formais": 1.9, "População_ocupada": 6.4, "Taxa_de_escolarização_de_6_a_14_anos_de_idade": 96.0, "Mortalidade_Infantil": 21.21, "Esgotamento_sanitário_adequado": 29.9}, {"Densidade_demográfica": 44.38, "Salário_médio_mensal_dos_trabalhadores_formais": 1.6, "População_ocupada": 8.7, "Taxa_de_escolarização_de_6_a_14_anos_de_idade": 98.6, "Mortalidade_Infantil": 16.81, "Esgotamento_sanitário_adequado": 59.5}, {"Densidade_demográfica": 50.05, "Salário_médio_mensal_dos_trabalhadores_formais": 1.7, "População_ocupada": 6.0, "Taxa_de_escolarização_de_6_a_14_anos_de_idade": 97.5, "Mortalidade_Infantil": 17.47, "Esgotamento_sanitário_adequado": 54.7}, {"Densidade_demográfica": 19.2, "Salário_médio_mensal_dos_trabalhadores_formais": 1.6, "População_ocupada": 6.5, "Taxa_de_escolarização_de_6_a_14_anos_de_idade": 95.0, "Mortalidade_Infantil": 44.78, "Esgotamento_sanitário_adequado": 40.2}, {"Densidade_demográfica": 106.93, "Salário_médio_mensal_dos_trabalhadores_formais": 1.5, "População_ocupada": 8.7, "Taxa_de_escolarização_de_6_a_14_anos_de_idade": 96.7, "Mortalidade_Infantil": 18.35, "Esgotamento_sanitário_adequado": 16.0}, {"Densidade_demográfica": 92.82, "Salário_médio_mensal_dos_trabalhadores_formais": 1.6, "População_ocupada": 6.5, "Taxa_de_escolarização_de_6_a_14_anos_de_idade": 94.1, "Mortalidade_Infantil": 17.24, "Esgotamento_sanitário_adequado": 39.0}, {"Densidade_demográfica": 134.78, "Salário_médio_mensal_dos_trabalhadores_formais": 1.5, "População_ocupada": 13.7, "Taxa_de_escolarização_de_6_a_14_anos_de_idade": 95.6, "Mortalidade_Infantil": 13.05, "Esgotamento_sanitário_adequado": 58.8}, {"Densidade_demográfica": 348.8, "Salário_médio_mensal_dos_trabalhadores_formais": 2.0, "População_ocupada": 18.7, "Taxa_de_escolarização_de_6_a_14_anos_de_idade": 96.9, "Mortalidade_Infantil": 8.67, "Esgotamento_sanitário_adequado": 63.3}, {"Densidade_demográfica": 127.18, "Salário_médio_mensal_dos_trabalhadores_formais": 1.8, "População_ocupada": 5.6, "Taxa_de_escolarização_de_6_a_14_anos_de_idade": 95.0, "Mortalidade_Infantil": 4.15, "Esgotamento_sanitário_adequado": 55.4}]}